mcp_server_threatbook/__init__.py
mcp_server_threatbook/server.py
mcp_server_threatbook-0.1.3.dist-info/METADATA
mcp_server_threatbook-0.1.3.dist-info/WHEEL
mcp_server_threatbook-0.1.3.dist-info/entry_points.txt
mcp_server_threatbook-0.1.3.dist-info/RECORD
