Metadata-Version: 2.4
Name: mcp-server-threatbook
Version: 0.1.3
Summary: Add your description here
Author-email: wowtalon <1120692265@qq.com>
Requires-Python: >=3.12
Requires-Dist: mcp[cli]>=1.9.1
Requires-Dist: requests>=2.32.3
